tagbot
