Metadata-Version: 1.0
Name: steem-tagbot
Version: 0.0.3
Summary: Random upvote bot on specific tags on steem network
Home-page: http://github.com/emre/tagbot
Author: emre yilmaz
Author-email: mail@emreyilmaz.me
License: MIT
Platform: UNKNOWN
